llama_index/packs/gradio_agent_chat/__init__.py
llama_index/packs/gradio_agent_chat/base.py
llama_index_packs_gradio_agent_chat-0.3.0.dist-info/METADATA
llama_index_packs_gradio_agent_chat-0.3.0.dist-info/WHEEL
llama_index_packs_gradio_agent_chat-0.3.0.dist-info/RECORD
